libsodium.a
libsodium.la
operations/__init__.py
operations/secure_random/__init__.py
operations/secure_random/test_secure_random.py
pkgconfig/libsodium.pc
tensorflow_encrypted-0.4.0.dist-info/METADATA
tensorflow_encrypted-0.4.0.dist-info/RECORD
tensorflow_encrypted-0.4.0.dist-info/WHEEL
tensorflow_encrypted-0.4.0.dist-info/top_level.txt
tests/__init__.py
tests/test_argmax.py
tests/test_batch2space.py
tests/test_batchnorm.py
tests/test_concat.py
tests/test_convert.py
tests/test_convolution.py
tests/test_int100_tensor.py
tests/test_int32_tensor.py
tests/test_int64_tensor.py
tests/test_lsb.py
tests/test_matmul.py
tests/test_maxpool2d.py
tests/test_odd_implicit.py
tests/test_pad.py
tests/test_pond_equal.py
tests/test_pooling.py
tests/test_prime_tensor.py
tests/test_private_compare.py
tests/test_private_model.py
tests/test_reduce_max.py
tests/test_reduce_sum.py
tests/test_relu.py
tests/test_reshape.py
tests/test_secure_model.py
tests/test_secure_random.py
tests/test_select_share.py
tests/test_share.py
tests/test_sigmoid.py
tests/test_stack.py
tests/test_strided_slice.py
tests/test_tanh.py
tests/test_truncate.py
tf_encrypted/__init__.py
tf_encrypted/config.py
tf_encrypted/private_model.py
tf_encrypted/session.py
tf_encrypted/types.py
tf_encrypted/convert/__init__.py
tf_encrypted/convert/convert.py
tf_encrypted/convert/register.py
tf_encrypted/layers/__init__.py
tf_encrypted/layers/activation.py
tf_encrypted/layers/batchnorm.py
tf_encrypted/layers/convolution.py
tf_encrypted/layers/core.py
tf_encrypted/layers/dense.py
tf_encrypted/layers/pooling.py
tf_encrypted/layers/reshape.py
tf_encrypted/operations/__init__.py
tf_encrypted/operations/secure_random/__init__.py
tf_encrypted/operations/secure_random/secure_random.py
tf_encrypted/operations/secure_random/secure_random_module.so
tf_encrypted/operations/secure_random/secure_random_module_tf_1.10.0.so
tf_encrypted/operations/secure_random/secure_random_module_tf_1.12.0.so
tf_encrypted/operations/secure_random/secure_random_module_tf_1.13.0-dev20181126.so
tf_encrypted/operations/secure_random/secure_random_module_tf_1.13.0-dev20190103.so
