Metadata-Version: 2.1
Name: tensorflow-encrypted
Version: 0.4.0
Summary: Layer on top of TensorFlow for doing machine learning on encrypted data.
Home-page: https://github.com/mortendahl/tf-encrypted
Author: Morten Dahl
Author-email: mortendahlcs@gmail.com
License: Apache License 2.0
Platform: UNKNOWN
Classifier: Programming Language :: Python :: 3
Classifier: License :: OSI Approved :: Apache Software License
Classifier: Development Status :: 2 - Pre-Alpha
Classifier: Operating System :: OS Independent
Classifier: Topic :: Scientific/Engineering :: Artificial Intelligence
Classifier: Topic :: Security :: Cryptography
Requires-Python: >=3.5
Requires-Dist: tensorflow (>=1.12.0)
Requires-Dist: numpy (>=1.14.0)
